README.md
setup.py
pytest_structmpd.egg-info/PKG-INFO
pytest_structmpd.egg-info/SOURCES.txt
pytest_structmpd.egg-info/dependency_links.txt
pytest_structmpd.egg-info/requires.txt
pytest_structmpd.egg-info/top_level.txt
structmpd/__init__.py
structmpd/plugin.py