Metadata-Version: 1.0
Name: pytest-structmpd
Version: 0.1.0
Summary: provide structured temporary directory
Home-page: https://github.com/disktnk/pytest-structmpd
Author: Daisuke Tanaka
Author-email: duaipp@gmail.com
License: UNKNOWN
Platform: UNKNOWN
